[
    {
        "question": "請告訴我如何乳癌防治",
        "answers": {
            "multilingual-e5": " 根據你所提供的文件片段，並沒有找到與「如何乳癌防治」相關的具體內容。因此，我無法從這段文字中提取任何與乳癌防治有關的訊息。若要獲得關於乳癌防治的資訊，建議搜尋其他資料來源。 ",
            "vanilla": " 乳癌防治的方法有很多，以下是幾個重要的方面：\n1. 健康生活方式：保持健康的體重、定期運動、均衡飲食和減少飲酒都有助於降低罹患乳癌的風險。\n2. 定期檢查：女性應該每年進行一次乳房X光攝影檢查，若發現早期乳癌，治癒的機率會比較高。此外，如果家族中有乳癌患者，更應提早開始定期檢查。\n3. 了解風險因素：了解哪些因素會增加罹患乳癌的風險，例如荷爾蒙水平、遺傳背景、生育史和環境因素等，可讓妳更清楚如何保護自己。\n4. 疫苗接種：目前有研究指出，注射人類乳突病毒（HPV）疫苗可能有助於降低乳癌風險。雖然不是絕對的預防方法，但值得考慮將此納入預防策略中。\n5. 及早發現：一旦發現乳房有任何異狀或疼痛，都應立即就醫",
            "chroma": " 根據你所提取的文字，我總結了與乳癌防治相關的建議和事實如下：\n\n1. 每月自我檢查乳房：定期檢查乳房可及早發現任何異常情況，但切勿過度緊張，若發現不對稱、疼痛或腫塊等症狀，應立即就醫。\n2. 每年定期篩檢：遵循醫生關於何時進行乳房X光攝影或超聲波檢查的建議，以檢測乳癌風險。\n3. 均衡飲食和持續運動：攝取富含營養的食物和維持活躍的生活方式有助於保持身體健康和免疫力，降低罹患乳癌的風險。\n4. 理想體重：維持健康的體重，避免過輕或過重，以降低乳癌風險。\n5. 早期診斷和治療：如出現疑似乳癌症狀，應立即就醫以獲得正確診斷和治療。\n6. 遺傳基因的影響：目前並無明確證據表明遺傳基因會影響罹患乳"
        },
        "message_id": 0,
        "docs": {
            "multilingual-e5": [
                {
                    "page_content": "I 7/30 Breakfast: soy milk",
                    "metadata": {
                        "source": "../textdata/text.txt"
                    }
                },
                {
                    "page_content": "I 7/22 Dinner: ramen",
                    "metadata": {
                        "source": "../textdata/text.txt"
                    }
                },
                {
                    "page_content": "I 7/21 Dinner: risotto",
                    "metadata": {
                        "source": "../textdata/text.txt"
                    }
                }
            ],
            "vanilla": [],
            "chroma": [
                {
                    "page_content": "1.乳癌症狀⼤多數為單側乳房產⽣不痛及不規則腫塊。\n  \n2.定期做乳房 X 光攝影及超⾳波檢查，能早期發現早期治療。\n  \n3.遺傳基因不會影響罹患乳癌的機率。\n  \n4.乳房⾃我檢查 4 要領為『視、觸、臥、擰』。\n  \n5.雌激素是誘發乳癌的因素之⼀。\n  \n評語\n    是否不知道\n是否不知道\n是否不知道\n是否不知道\n是否不知道\n臺中榮⺠總醫院\n407219臺中市⻄屯區臺灣⼤道四段 1650 號\n總機： (04)2359-2525\n全⼈智慧  醫療典範\n愛⼼品質  創新當責\n本站內容為臺中榮⺠總醫院所有，未經允許請勿任意轉載ヽ複製或做商業⽤途",
                    "metadata": {
                        "page": 3,
                        "source": "/Users/namwoam/rep/rag-prototype/dataset/med-info/乳癌的認識與自我檢查 _ 臺中榮民總醫院護理衛教.pdf",
                        "start_index": 360
                    }
                },
                {
                    "page_content": "C. 以右⼿檢查左邊乳房、⽅法與站著摸⼀樣。    \nD. 以同⼀⽅式檢查右乳。\n4. 擰:擰（擠）以⼤拇指及食指擠壓看看是否有硬塊或淋巴結腫⼤、乳頭是否有分泌物流出。  \n \n八、乳房保健之道\n1. 每⽉⾃我檢查。\n2. 每年定期篩檢。\n3. ⾼纖飲食。\n4. 持續運動。\n5. 理想的體重。\n6. 節制飲酒。\n7. 充⾜的睡眠。\n8. 正常的作息。",
                    "metadata": {
                        "page": 2,
                        "source": "/Users/namwoam/rep/rag-prototype/dataset/med-info/乳癌的認識與自我檢查 _ 臺中榮民總醫院護理衛教.pdf",
                        "start_index": 470
                    }
                },
                {
                    "page_content": "發現早期治療。\n \n⼗、參考資料\n1. 朱峻⽥、李儼庭、張峻嘉、周芷佑、陳⺠虹（ 2022 ）‧台灣乳癌篩檢策略‧家庭醫學與基層醫療， 37(4) ， 119-124 。\n2. 衛⽣福利部統計處（ 2022 年  6 ⽉  30 ⽇）‧ 110 年國⼈死因統計結果。 https://www .mohw .gov.tw/cp-16-70314-\n1.html\n乳癌的認識與⾃我檢查簡易測驗\n讓我們來進⾏測驗，以確認您已充分了解。\n1.乳癌症狀⼤多數為單側乳房產⽣不痛及不規則腫塊。\n  \n2.定期做乳房 X 光攝影及超⾳波檢查，能早期發現早期治療。\n  \n3.遺傳基因不會影響罹患乳癌的機率。",
                    "metadata": {
                        "page": 3,
                        "source": "/Users/namwoam/rep/rag-prototype/dataset/med-info/乳癌的認識與自我檢查 _ 臺中榮民總醫院護理衛教.pdf",
                        "start_index": 145
                    }
                }
            ]
        }
    },
    {
        "question": "如何維持健康的體重？",
        "answers": {
            "multilingual-e5": " 根據所提供的文字片段，並沒有找到任何關於如何維持健康的體重的資訊。因此，我無法為您提供與維持健康體重相關的具體建議或策略。如果您想了解更多關於健康體重管理的資訊，建議您查閱相關書籍、文章或諮詢專業醫生和營養師。 ",
            "vanilla": " 要維持健康的體重，可以從控制飲食和增加運動量兩方面著手。在飲食上，應保持低脂、低糖、高纖的均衡飲食習慣，少吃高熱量、高脂肪的食物；同時，要定時用餐，避免暴飲暴食。此外，多喝水能幫助新陳代謝，也有助於減少飢餓感。在運動方面，每週至少進行150分鐘的中等強度有氧運動，如快走、游泳、騎車等，也可加入肌力訓練，強化肌肉以提高基礎代謝率。另外，充足的睡眠也有助於體重管理，因為睡眠不足會影響荷爾蒙分泌，導致食慾失控和能量消耗降低。最後，控制飲食和增加運動量是維持健康體重的關鍵，持之以恆地執行這些習慣才能達到理想的效果。 ",
            "chroma": " 根據所提供的文本，維持健康的體重與生活習慣相關，其中包含均衡飲食、規律運動和充足睡眠。\n\n1. 均衡飲食：\n(a) 控制熱量攝取：計算個人基礎代謝率（BMR）並加上活動能量消耗（TDEE），以確定每日所需熱量攝取。利用線上熱量計算器或營養追蹤應用程式協助管理熱量攝入。\n(b) 遵循「我的餐盤」指南：將食物分為穀類、蛋白質、蔬菜和水果四大類，每餐均勻分配各別類別的份量，並注意少油、少鹽、少糖的烹調方式。\n(c) 減少加工食品和甜飲的攝取：多選擇天然、新鮮的食物，以降低鈉含量和反式脂肪酸的攝入。\n2. 規律運動：\n(a) 每週從事至少150分鐘的中度身體活動，如快"
        },
        "message_id": 1,
        "docs": {
            "multilingual-e5": [
                {
                    "page_content": "I 7/30 Breakfast: soy milk",
                    "metadata": {
                        "source": "../textdata/text.txt"
                    }
                },
                {
                    "page_content": "I 7/24 Breakfast: congee",
                    "metadata": {
                        "source": "../textdata/text.txt"
                    }
                },
                {
                    "page_content": "I 7/28 Breakfast: yogurt",
                    "metadata": {
                        "source": "../textdata/text.txt"
                    }
                }
            ],
            "vanilla": [],
            "chroma": [
                {
                    "page_content": "或湯。\n3.避免甜點、油脂及油炸食物。\n4.依醫師指⽰服⽤⽌吐劑。\n5.多休息。\n6.⽤餐後或睡前⼝腔清潔，嘔吐後應漱\n⼝，以維持⼝腔清潔與舒適。\n食慾低下\n 1.少量多餐進食。\n2.與別⼈⼀同⽤餐。\n3.選擇⾃⼰喜歡的食物。\n4.儘量攝取⾼熱量、⾼蛋⽩或⾼營養的食\n物。\n5.食⽤飲食代⽤品，例如：奶昔或冰淇淋\n等⾼熱量食物。",
                    "metadata": {
                        "page": 2,
                        "source": "/Users/namwoam/rep/rag-prototype/dataset/med-info/化學藥物治療須知 _ 臺中榮民總醫院護理衛教.pdf",
                        "start_index": 210
                    }
                },
                {
                    "page_content": "4.攝取豐富的蛋⽩質如⾁、⿂、蛋、豆類，增加⾝體抵抗⼒；如出現進食困難或食慾不佳，可與營養師或醫師討論是\n否有需要加入⾼蛋⽩粉於飲食中。\n  \n5.避免過熱、堅硬、粗糙、酸性柑橘類、含咖啡因食物，不要吸菸。\n  \n評語\n    是否不知道\n是否不知道\n是否不知道\n是否不知道\n是否不知道\n臺中榮⺠總醫院\n407219臺中市⻄屯區臺灣⼤道四段 1650 號\n總機： (04)2359-2525",
                    "metadata": {
                        "page": 3,
                        "source": "/Users/namwoam/rep/rag-prototype/dataset/med-info/放射線治療須知 _ 臺中榮民總醫院護理衛教.pdf",
                        "start_index": 1772
                    }
                },
                {
                    "page_content": "B. ⼿腳拉筋舒展，維持四肢肌⾁的柔軟及彈性。\nC. 若體⼒許可，每週進⾏三⾄五次 30 分鐘的低強度有氧運動，例如：慢⾛、游泳、腳踏⾞。\n4. 預防意外⼑割傷：\nA. 清洗碗盤、⼾外活動或是維修物品時戴上⼿套保護雙⼿。\nB. ⼩⼼處理尖銳物品，避免意外割傷⾃⼰。",
                    "metadata": {
                        "page": 2,
                        "source": "/Users/namwoam/rep/rag-prototype/dataset/med-info/認識化學治療相關周邊神經病變 _ 臺中榮民總醫院護理衛教.pdf",
                        "start_index": 403
                    }
                }
            ]
        },
        "feedback": {
            "multilingual-e5": {
                "type": "faces",
                "score": "😀",
                "text": null
            },
            "vanilla": {
                "type": "faces",
                "score": "😐",
                "text": null
            },
            "chroma": {
                "type": "faces",
                "score": "😀",
                "text": null
            }
        }
    }
]